stackwhy/__init__.py
stackwhy/__main__.py
stackwhy/cli.py
stackwhy/event.py
stackwhy/py.typed
stackwhy/stack_why.py
stackwhy/version/VERSION
stackwhy/version/__init__.py
stackwhy/version/py.typed
stackwhy-1.0.1.dist-info/LICENSE
stackwhy-1.0.1.dist-info/METADATA
stackwhy-1.0.1.dist-info/WHEEL
stackwhy-1.0.1.dist-info/entry_points.txt
stackwhy-1.0.1.dist-info/top_level.txt
stackwhy-1.0.1.dist-info/RECORD
