Metadata-Version: 2.1
Name: stackwhy
Version: 1.0.1
Summary: CLI tool and package for visualising the most recent events on an Amazon Web Services CloudFormation stack
Home-page: https://github.com/cariad/stackwhy
Author: Cariad Eccleston
Author-email: cariad@cariad.earth
License: MIT
Platform: UNKNOWN
Classifier: Development Status :: 5 - Production/Stable
Classifier: Environment :: Console
Classifier: License :: OSI Approved :: MIT License
Classifier: Natural Language :: English
Classifier: Operating System :: OS Independent
Classifier: Programming Language :: Python :: 3 :: Only
Classifier: Programming Language :: Python :: 3.8
Classifier: Programming Language :: Python :: 3.9
Classifier: Topic :: Software Development :: Testing
Classifier: Topic :: Utilities
Classifier: Typing :: Typed
Requires-Python: >=3.8
License-File: LICENSE
Requires-Dist: ansiscape (<2.0,>=1.1)
Requires-Dist: boto3 (<2.0,>=1.18)
Requires-Dist: tabulate (<1.0,>=0.8)
